lbpqca-0.1.1.dist-info/licenses/LICENSE
scr/lbpqca/__init__.py
scr/lbpqca/matrix.py
scr/lbpqca/polynomial.py
scr/lbpqca/type_aliases.py
scr/lbpqca/lattice/__init__.py
scr/lbpqca/lattice/attacks.py
scr/lbpqca/lattice/reductions_lattice.py
scr/lbpqca/lattice/reductions_problems.py
lbpqca-0.1.1.dist-info/METADATA
lbpqca-0.1.1.dist-info/WHEEL
lbpqca-0.1.1.dist-info/top_level.txt
lbpqca-0.1.1.dist-info/RECORD
