Metadata-Version: 2.4
Name: lbpqca
Version: 0.1.1
Summary: Library wo lattice attact cryptography
Author-email: Kamil Karaś <kkaras@student.agh.edu.pl>
License: MIT
Classifier: Programming Language :: Python :: 3
Classifier: License :: OSI Approved :: MIT License
Classifier: Operating System :: OS Independent
Requires-Python: >=3.12
License-File: LICENSE
Dynamic: license-file
